{
  "kind": "collectionType",
  "collectionName": "reviews",
  "info": {
    "singularName": "review",
    "pluralName": "reviews",
    "displayName": "Review",
    "description": ""
  },
  "options": {
    "draftAndPublish": true
  },
  "pluginOptions": {},
  "attributes": {
    "name": {
      "type": "string",
      "required": true,
      "unique": true
    },
    "review_star": {
      "type": "integer",
      "required": true,
      "min": 1,
      "max": 5
    },
    "job": {
      "type": "string",
      "required": false
    },
    "image": {
      "type": "media",
      "multiple": false,
      "required": false,
      "allowedTypes": [
        "images",
        "files",
        "videos",
        "audios"
      ]
    },
    "reviewDesc": {
      "type": "blocks",
      "required": true
    }
  }
}
